appops/__init__.py
appops/hooks/__init__.py
appops/hooks/admob.py
appops/hooks/oauth2discoveryapi.py
appops/operators/__init__.py
appops/operators/admob_to_postgres.py
airflow_provider_appops-0.0.4.dist-info/METADATA
airflow_provider_appops-0.0.4.dist-info/WHEEL
airflow_provider_appops-0.0.4.dist-info/entry_points.txt
airflow_provider_appops-0.0.4.dist-info/top_level.txt
airflow_provider_appops-0.0.4.dist-info/RECORD
