Metadata-Version: 2.1
Name: airflow-provider-appops
Version: 0.0.4
Summary: App ops provider package built by papaya.
Home-page: https://github.com/wbchn/apache-airflow-providers-appops
Author: wb
Author-email: wbin.chn@gmail.com
Maintainer: wbchn
Maintainer-email: wbin.chn@gmail.com
License: Apache License 2.0
Platform: UNKNOWN
Classifier: License :: OSI Approved :: MIT License
Classifier: Programming Language :: Python
Classifier: Programming Language :: Python :: 3
Classifier: Programming Language :: Python :: 3.7
Classifier: Programming Language :: Python :: 3.8
Classifier: Intended Audience :: Developers
Requires-Python: ~=3.7
Requires-Dist: apache-airflow (<2.3,>=2.1)
Requires-Dist: apache-airflow-providers-google (<7.0.0,>=5.0.0)
Requires-Dist: protobuf (<=3.20.2)
